btreeny/__init__.py
btreeny/_ctx.py
btreeny/_get_name.py
btreeny/_tree_status.py
btreeny/py.typed
btreeny/viz.py
btreeny-0.1.5.dist-info/METADATA
btreeny-0.1.5.dist-info/WHEEL
btreeny-0.1.5.dist-info/licenses/LICENSE
btreeny-0.1.5.dist-info/RECORD
