Metadata-Version: 2.4
Name: btreeny
Version: 0.1.5
Summary: Add your description here
Author-email: Tim Lingard <tklingard@gmail.com>
License-File: LICENSE
Requires-Python: >=3.10
